<mos>
<mosID>MOS26.MOS</mosID>
<ncsID>MOS26.NCS</ncsID>
<roListAll>
<roID>DEMOENPS50VPC;P_OSM\W;AADC7235-007A-4317-BE112095DF74356A</roID>
<roSlug>OSM Dev change</roSlug>
<roChannel></roChannel>
<roEdStart>2037-05-16T14:00:00</roEdStart>
<roEdDur>00:30:00</roEdDur>
<roTrigger></roTrigger>
<roMacroIn></roMacroIn>
<roMacroOut></roMacroOut>
<mosExternalMetadata>
<mosScope>PLAYLIST</mosScope>
<mosSchema>http://DEMOENPS50VPC/schema/enpsro.dtd</mosSchema>
<mosPayload>
<roMOSIDList>
MOS25.MOS;MOS26.MOS;MOS28.MOS;MOS281.MOS</roMOSIDList>
</mosPayload>
</mosExternalMetadata>

<roID>DEMOENPS50VPC;P_OSM\W;6EEF52CC-59E2-4B8E-BABB7544CD07D7F1</roID>
<roSlug>OSM Dev 2</roSlug>
<roChannel></roChannel>
<roEdStart>2037-05-16T14:00:00</roEdStart>
<roEdDur>00:30:00</roEdDur>
<roTrigger></roTrigger>
<roMacroIn></roMacroIn>
<roMacroOut></roMacroOut>
<mosExternalMetadata>
<mosScope>PLAYLIST</mosScope>
<mosSchema>http://DEMOENPS50VPC/schema/enpsro.dtd</mosSchema>
<mosPayload>
<roMOSIDList>
MOS25.MOS;MOS26.MOS;MOS28.MOS;MOS281.MOS</roMOSIDList>
</mosPayload>
</mosExternalMetadata>

</roListAll>
</mos>
